Workbook

Sheet Historial de contabilizaciones
A1: Fecha | B1: DÍA | C1: MES/AÑO | D1: Descripcion | E1: Entrada | F1: Salida | G1: Total | H1: ID_Registro | I1: DATAFONO | J1: Efectivo a nequi | K1: Pasa nequi a efectivo | L1: NEQUI | M1: Efectivo a daviplata | N1: pasa daviplata a efectivo | O1: DAVIPLATA | P1: Costo | Q1: INVENTARIO | R1: Cantidad dada | S1: CRÉDITO | T1: PagoCxp | U1: CxP | V1: Distribucion utilidades | W1: Ajuste a efectivo | X1: ajuste a datafono | Y1: ajuste a nequi | Z1: Ajuste a daviplata | AA1: ajuste a credito | AB1: caja mayor
A2: 45220 | B2: =TEXT(A2,"dddd") | C2: =TEXT(A2,"mmmm")&TEXT(A2,"yy") | D2: abono for explorer | E2: 600000 | G2: =SUM(E2:F2)
A3: 45220 | B3: =TEXT(A3,"dddd") | C3: =TEXT(A3,"mmmm")&TEXT(A3,"yy") | D3: 189 fiat cielo | E3: 189000 | G3: =SUM(E3:F3)
A4: 45220 | B4: =TEXT(A4,"dddd") | C4: =TEXT(A4,"mmmm")&TEXT(A4,"yy") | D4: ford explorer completa abono | E4: 300000 | F4: =23*432 | G4: =SUM(E4:F4)
A5: 45220 | B5: =TEXT(A5,"dddd") | C5: =TEXT(A5,"mmmm")&TEXT(A5,"yy") | D5: fusibles | E5: 2000 | G5: =SUM(E5:F5) | I5: =SUM(E2:F9)
A6: 45223 | B6: =TEXT(A6,"dddd") | C6: =TEXT(A6,"mmmm")&TEXT(A6,"yy") | D6: gastos representacion | E6: =E5+E2 | F6: -1000 | G6: =SUM(E6:F6)
A7: 45223 | B7: =TEXT(A7,"dddd") | C7: =TEXT(A7,"mmmm")&TEXT(A7,"yy") | D7: compra thiner | F7: -13600 | G7: =SUM(E7:F7)
A8: 45223 | B8: =TEXT(A8,"dddd") | C8: =TEXT(A8,"mmmm")&TEXT(A8,"yy") | D8: gastos representaicon | F8: -1900 | G8: =SUM(E8:F8)
A9: 45332 | B9: =TEXT(A9,"dddd") | C9: =TEXT(A9,"mmmm")&TEXT(A9,"yy") | D9: nomina joseph | F9: -184000 | G9: =SUM(E9:F9)
A10: 45332 | B10: =TEXT(A10,"dddd") | C10: =TEXT(A10,"mmmm")&TEXT(A10,"yy") | D10: davipata pagaron 390 ahorita a juan, no se sabe de qué | E10: 390000 | G10: =SUM(E10:F10) | O10: 1
A11: 45332 | B11: =TEXT(A11,"dddd") | C11: =TEXT(A11,"mmmm")&TEXT(A11,"yy") | D11: william hay que darle 30 de gasolina de blazer que se usó | G11: =SUM(E11:F11)
A12: 45332 | B12: =TEXT(A12,"dddd") | C12: =TEXT(A12,"mmmm")&TEXT(A12,"yy") | D12: cambio efectivo nequi joseph mil. 1 | G12: =SUM(E12:F12) | J12: 1000
A13: 45334 | B13: =TEXT(A13,"dddd") | C13: =TEXT(A13,"mmmm")&TEXT(A13,"yy") | D13: edison repuestos manigueta moto que se rompio | F13: -20000 | G13: =SUM(E13:F13)
A14: 45334 | B14: =TEXT(A14,"dddd") | C14: =TEXT(A14,"mmmm")&TEXT(A14,"yy") | D14: gasolina twingo sebas | F14: -10000 | G14: =SUM(E14:F14)
A15: 45334 | B15: =TEXT(A15,"dddd") | C15: =TEXT(A15,"mmmm")&TEXT(A15,"yy") | D15: empaque exosto aveo | E15: 10000 | G15: =SUM(E15:F15)
A16: 45334 | B16: =TEXT(A16,"dddd") | C16: =TEXT(A16,"mmmm")&TEXT(A16,"yy") | D16: cambio nequi efectivo brayan | G16: =SUM(E16:F16) | K16: 50000
A17: 45353 | B17: =TEXT(A17,"dddd") | C17: =TEXT(A17,"mmmm")&TEXT(A17,"yy") | D17: taxi spark por tarjeta | E17: 414000 | G17: =SUM(E17:F17) | I17: 1
A18: 45353 | B18: =TEXT(A18,"dddd") | C18: =TEXT(A18,"mmmm")&TEXT(A18,"yy") | D18: wagon tarjeta | E18: 230000 | G18: =SUM(E18:F18) | I18: 1
A19: 45353 | B19: =TEXT(A19,"dddd") | C19: =TEXT(A19,"mmmm")&TEXT(A19,"yy") | D19: taxis por nequi | E19: 1050000 | G19: =SUM(E19:F19) | L19: 1
A20: 45353 | B20: =TEXT(A20,"dddd") | C20: =TEXT(A20,"mmmm")&TEXT(A20,"yy") | D20: nomina | F20: -550000 | G20: =SUM(E20:F20)
A21: 45355 | B21: =TEXT(A21,"dddd") | C21: =TEXT(A21,"mmmm")&TEXT(A21,"yy") | D21: cambio nequi efectivo 16 | G21: =SUM(E21:F21) | K21: 16000

Sheet productos
A1: Codigo | B1: Descripcion | C1: MARCA | D1: PRECIO | E1: COSTO | F1: Categoria | G1: ALMACÉN | H1: STOCK MÍNIMO | I1: EXISTENCIA ACTUAL | J1: CODIGO UNITARIO | K1: cantidad conjunta
A2: ABRABARR9 | B2: abrazadera barra estabilizadora r9 | C2: BOLSA SUELTO | D2: 12000 | E2: 3161.592 | F2: abrazadera barra estabilizadora | G2: 5B | I2: =SUMIFS('entradas y salidas'!I:I,'entradas y salidas'!B:B,productos!A2) | J2: ABRABARR9 | K2: =SUMIFS(I:I,J:J,J2)
A3: 3/4abraza | B3: abrazadera metalica 3/4 pulgadas pequeña | C3: BOLSA TRANSPARENTE | D3: 1000 | E3: 0.016 | F3: abrazadera metalica | G3: 9C-10 | I3: =SUMIFS('entradas y salidas'!I:I,'entradas y salidas'!B:B,productos!A3) | J3: 3/4abraza | K3: =SUMIFS(I:I,J:J,J3)
A4: abrametcom | B4: abrazadera metalica comun que mas hay | C4: suelta | D4: 1800 | F4: abrazadera metalica | G4: 9c-8 | I4: =SUMIFS('entradas y salidas'!I:I,'entradas y salidas'!B:B,productos!A4) | J4: abrametcom | K4: =SUMIFS(I:I,J:J,J4)
A5: abra1004 | B5: abrazaderametalica titan para manguera 3/8 pulgadas. min 5/16'' max 5/8'' | C5: titan bolsa | D5: 1000 | E5: 560 | F5: abrazadera metalica | G5: 9c-8 | I5: =SUMIFS('entradas y salidas'!I:I,'entradas y salidas'!B:B,productos!A5) | J5: abra1004 | K5: =SUMIFS(I:I,J:J,J5)
A6: abra1006 | B6: abrazdadera metalica titan para manguera 1/2 pulgada min 7/16'' max 25/32'' | C6: titan bolsa | D6: 1000 | E6: 580 | F6: abrazadera metalica | G6: 9c-8 | I6: =SUMIFS('entradas y salidas'!I:I,'entradas y salidas'!B:B,productos!A6) | J6: abra1006 | K6: =SUMIFS(I:I,J:J,J6)
A7: abra4028 | B7: abrazadera metalica titan min 1*1/4'' max 2'' | C7: titan bolsa | D7: 5000 | E7: 1950 | F7: abrazadera metalica | G7: 9c-8 | I7: =SUMIFS('entradas y salidas'!I:I,'entradas y salidas'!B:B,productos!A7) | J7: abra4028 | K7: =SUMIFS(I:I,J:J,J7)
A8: abra4016 | B8: abrazadera metalica titan min 23 max 35 mm | C8: titan bolsa | E8: 1600 | F8: abrazadera metalica | G8: 9c-8 | I8: =SUMIFS('entradas y salidas'!I:I,'entradas y salidas'!B:B,productos!A8) | J8: abra4016 | K8: =SUMIFS(I:I,J:J,J8)
A9: MK-131-N | B9: abrazadera larga y ancha plástica 7,2*500 mm | C9: MAK | D9: 1500 | E9: 280 | F9: abrazaderas | G9: 7 | I9: =SUMIFS('entradas y salidas'!I:I,'entradas y salidas'!B:B,productos!A9) | J9: MK-131-N | K9: =SUMIFS(I:I,J:J,J9)
A10: mk-125-n | B10: abrazadera plastica mediana de 4,8* 300mm | C10: mak | D10: 1000 | E10: 130 | F10: abrazaderas | G10: 7 | I10: =SUMIFS('entradas y salidas'!I:I,'entradas y salidas'!B:B,productos!A10) | J10: mk-125-n | K10: =SUMIFS(I:I,J:J,J10)
A11: mk-127-n | B11: abrazadea plastico 4,8*400mm | C11: mak | D11: 1000 | E11: 160 | F11: abrazaderas | G11: 7 | I11: =SUMIFS('entradas y salidas'!I:I,'entradas y salidas'!B:B,productos!A11) | J11: mk-127-n | K11: =SUMIFS(I:I,J:J,J11)
A12: mk-129-n | B12: abrazadera plastica 4,8*200 pequeña | C12: MAK | D12: 700 | E12: 80 | F12: abrazaderas | I12: =SUMIFS('entradas y salidas'!I:I,'entradas y salidas'!B:B,productos!A12) | J12: mk-129-n | K12: =SUMIFS(I:I,J:J,J12)
A13: 5W-30 | B13: aceite 1/4 mobil super 5w-30 3000 | C13: MOBIL | D13: 50000 | F13: aceite | I13: =SUMIFS('entradas y salidas'!I:I,'entradas y salidas'!B:B,productos!A13) | J13: 5W-30 | K13: =SUMIFS(I:I,J:J,J13)
A14: 5W-40 | B14: aceite 1/4 5w-40 | C14: MOBIL | D14: 40000 | F14: aceite | I14: =SUMIFS('entradas y salidas'!I:I,'entradas y salidas'!B:B,productos!A14) | J14: 5W-40 | K14: =SUMIFS(I:I,J:J,J14)
A15: ACEGRANG | B15: galon aceite granel (se consume 2,5 cm de altura) | C15: GRANEL | D15: 80000 | E15: 70000 | F15: aceite | I15: =SUMIFS('entradas y salidas'!I:I,'entradas y salidas'!B:B,productos!A15) | J15: ACEGRANG | K15: =SUMIFS(I:I,J:J,J15)
A16: 10W302 | B16: galon aceite mobil super 2000 10w-30 | C16: MOBIL | D16: 125000 | F16: aceite | I16: =SUMIFS('entradas y salidas'!I:I,'entradas y salidas'!B:B,productos!A16) | J16: 10W302 | K16: =SUMIFS(I:I,J:J,J16)
A17: ACEGRANC | B17: 1/4 aceite a granel (consume 0,6 cm de altura) | C17: GRANEL | D17: 20000 | E17: 17000 | F17: aceite | I17: =SUMIFS('entradas y salidas'!I:I,'entradas y salidas'!B:B,productos!A17) | J17: ACEGRANC | K17: =SUMIFS(I:I,J:J,J17)
A18: 20W-50M | B18: aceite 1/4 mobil super 20w-50 1000 | C18: MOBIL | D18: 30000 | F18: aceite | I18: =SUMIFS('entradas y salidas'!I:I,'entradas y salidas'!B:B,productos!A18) | J18: 20W-50M | K18: =SUMIFS(I:I,J:J,J18)
A19: SAE50M | B19: aceite 1/4 sae 50 mobil special hd | C19: MOBIL | D19: 28000 | E19: 18000 | F19: aceite | I19: =SUMIFS('entradas y salidas'!I:I,'entradas y salidas'!B:B,productos!A19) | J19: SAE50M | K19: =SUMIFS(I:I,J:J,J19)
A20: 10W30M | B20: aceite 1/4 mobil super 10w-30 2000 | C20: MOBIL | D20: 33000 | E20: 26000 | F20: aceite | I20: =SUMIFS('entradas y salidas'!I:I,'entradas y salidas'!B:B,productos!A20) | J20: 10W30M | K20: =SUMIFS(I:I,J:J,J20)
A21: 15W40D | B21: galon aceite mobil delvac mx esp 15w-40 | C21: MOBIL | D21: 105000 | F21: aceite | I21: =SUMIFS('entradas y salidas'!I:I,'entradas y salidas'!B:B,productos!A21) | J21: 15W40D | K21: =SUMIFS(I:I,J:J,J21)
A22: SAE50GAL | B22: galon aceite mobil sae 50 special hd | C22: MOBIL | D22: 105000 | E22: 90000 | F22: aceite | I22: =SUMIFS('entradas y salidas'!I:I,'entradas y salidas'!B:B,productos!A22) | J22: SAE50GAL | K22: =SUMIFS(I:I,J:J,J22)
A23: KSL-2012 | B23: bieleta estabilizadora hyundai i10 kia picanto izquierdo | C23: KTC | D23: 20000 | F23: muñeco | G23: 2A-2 | I23: =SUMIFS('entradas y salidas'!I:I,'entradas y salidas'!B:B,productos!A23) | J23: KSL-2012
A24: KRE-3106 | B24: axial hyundai i10 kia picanto | C24: KTC | F24: axial | G24: 2c-2 | I24: =SUMIFS('entradas y salidas'!I:I,'entradas y salidas'!B:B,productos!A24) | J24: KRE-3106
A25: hy07287 | B25: soporte motor kia picanto ekotaxi i10 tras bieleta | C25: effix | F25: soporte motor | G25: estante maquina inyectores - A | I25: =SUMIFS('entradas y salidas'!I:I,'entradas y salidas'!B:B,productos!A25) | J25: hy07287
A26: hy07235 | B26: soporte motor kia picanto morning 05 11 i10 09 15 tras | C26: effix | F26: soporte motor | G26: estante maquina inyectores - A | I26: =SUMIFS('entradas y salidas'!I:I,'entradas y salidas'!B:B,productos!A26) | J26: hy07235
A27: hy02002/25100-02400 | B27: bomba agua hyundai atos kia picanto 1,1 | C27: onnuri | F27: bomba de agua | G27: estante maquina inyectores - A | I27: =SUMIFS('entradas y salidas'!I:I,'entradas y salidas'!B:B,productos!A27) | J27: hy02002/25100-02400
A28: 7390-BKR5EY | B28: bujia copa 16 | C28: NGK | F28: bujias | G28: 12c | I28: =SUMIFS('entradas y salidas'!I:I,'entradas y salidas'!B:B,productos!A28) | J28: 7390-BKR5EY
A29: cv01129/96325246 | B29: bomba aceite chevrolet spark 724 chronos daewoo matiz | C29: onnuri | F29: bomba de aceite | G29: estante maquina inyectores - A | I29: =SUMIFS('entradas y salidas'!I:I,'entradas y salidas'!B:B,productos!A29) | J29: cv01129/96325246
A30: rn07014 | B30: soporte motor renault megane 2 scenic 2 trasero | C30: effix | F30: soporte motor | G30: estante maquina inyectores - A | I30: =SUMIFS('entradas y salidas'!I:I,'entradas y salidas'!B:B,productos!A30) | J30: rn07014
A31: rn07131 | B31: tijera renault duster delantero derecha | C31: effix | F31: tijera | G31: 6a | I31: =SUMIFS('entradas y salidas'!I:I,'entradas y salidas'!B:B,productos!A31) | J31: rn07131
A32: hy01098 | B32: tensorcorrea reparticion atos santro kia picanto | C32: kbs | F32: tensor | G32: 2b-4c | I32: =SUMIFS('entradas y salidas'!I:I,'entradas y salidas'!B:B,productos!A32) | J32: hy01098
A33: cv01049/90499401 | B33: tensor correa distrivusion chevrolet corsa daewoo cielo racer aveo pequeño | C33: kbs | F33: rodamiento | I33: =SUMIFS('entradas y salidas'!I:I,'entradas y salidas'!B:B,productos!A33) | J33: cv01049/90499401
A34: cv08054 | B34: rodillo rueda del chev corsa | C34: kbs | F34: rodamiento | G34: 11d-a4 | I34: =SUMIFS('entradas y salidas'!I:I,'entradas y salidas'!B:B,productos!A34) | J34: cv08054
A35: rn8008 | B35: rodamiento tras renault logan sandero stepway bolas | C35: kbs | F35: rodamiento | G35: 2b-2b | I35: =SUMIFS('entradas y salidas'!I:I,'entradas y salidas'!B:B,productos!A35) | J35: rn8008
A36: rn08007 | B36: rodamiento rueda tras renault logan sandero agujas | C36: kbs | F36: rodamiento | G36: 2b-2a | I36: =SUMIFS('entradas y salidas'!I:I,'entradas y salidas'!B:B,productos!A36) | J36: rn08007
A37: hy08018/51720-2k00 | B37: rodamiento delantero hyundai i35 kia soul cerato forte koup veloster | C37: kbs | F37: rodamiento | G37: 11d-a7 | I37: =SUMIFS('entradas y salidas'!I:I,'entradas y salidas'!B:B,productos!A37) | J37: hy08018/51720-2k00
A38: 24422061 | B38: balinera de clos corsa evolution onix soni | C38: supi | F38: balinera | G38: caja encintada | I38: =SUMIFS('entradas y salidas'!I:I,'entradas y salidas'!B:B,productos!A38) | J38: 24422061
A39: 30985x20 | B39: correa reparticion 125 dientes motor 200 daewoo espero aranos kadett ipanema monza | C39: gates | F39: correa reparticion | G39: 11e-a3 | I39: =SUMIFS('entradas y salidas'!I:I,'entradas y salidas'!B:B,productos!A39) | J39: 30985x20
A40: hy01096/24410-22020 | B40: tensor correa distribución hyundai accent next verna gyro vision rio xcite | C40: kbs | F40: rodamiento | G40: 11d-a5 | I40: =SUMIFS('entradas y salidas'!I:I,'entradas y salidas'!B:B,productos!A40) | J40: hy01096/24410-22020

Sheet entradas y salidas
A1: Fecha | B1: Codigo | C1: Descripcion | D1: Marca | E1: Categoria | F1: almacen | G1: Codigo unitario | H1: Mes/año | I1: cantidad | J1: observaciones | K1: ID_registro | L1: Cliente | M1: ¿devolución? | N1: ¿perdida anormal? | O1: Aumento anormal | P1: Cant Perdida | Q1: Devolucion a proveedor | R1: cliente nos devuelve | S1: CANT VENDIDA | T1: CANT ADQUIRIDA | U1: Costo ventas | V1: Costo adquisiciones | W1: Costo unitario | X1: precio unitario
A2: 45260 | B2: KSL-2012 | C2: bieleta estabilizadora hyundai i10 kia picanto izquierdo | D2: KTC | E2: muñeco | F2: 2A-2 | G2: 0 | H2: =TEXT(A2,"MMMM") & TEXT(A2,"yy") | I2: 2 | O2: =IF(N2=1,SUMIF(I2,">0"),0) | P2: =IF(N2=1,SUMIF(I2,"<0")*-1,0) | Q2: =IF(M2=1,SUMIF(I2,"<0")*-1,0) | R2: =IF(M2=1,SUMIF(I2,">0"),0) | S2: =SUMIFS(I2,I2,"<0",M2,"",N2,"") | T2: =SUMIFS(I2,I2,">0",M2,"",N2,"") | U2: =IFERROR((S2*W2)*-1,0) | V2: =IFERROR(T2*W2,0) | W2: =VLOOKUP(B2,productos!A:K,5,FALSE) | X2: =VLOOKUP(B2,productos!A:K,4,FALSE)
A3: 45260 | B3: KRE-3106 | C3: axial hyundai i10 kia picanto | D3: KTC | E3: axial | F3: 2c-2 | G3: 0 | H3: =TEXT(A3,"MMMM") & TEXT(A3,"yy") | I3: 3 | O3: =IF(N3=1,SUMIF(I3,">0"),0) | P3: =IF(N3=1,SUMIF(I3,"<0")*-1,0) | Q3: =IF(M3=1,SUMIF(I3,"<0")*-1,0) | R3: =IF(M3=1,SUMIF(I3,">0"),0) | S3: =SUMIFS(I3,I3,"<0",M3,"",N3,"") | T3: =SUMIFS(I3,I3,">0",M3,"",N3,"") | U3: =IFERROR((S3*W3)*-1,0) | V3: =IFERROR(T3*W3,0) | W3: =VLOOKUP(B3,productos!A:K,5,FALSE) | X3: =VLOOKUP(B3,productos!A:K,4,FALSE)
A4: 45260 | B4: hy07287 | C4: soporte motor kia picanto ekotaxi i10 tras bieleta | D4: effix | E4: soporte motor | F4: estante maquina inyectores - A | H4: =TEXT(A4,"MMMM") & TEXT(A4,"yy") | I4: 1 | O4: =IF(N4=1,SUMIF(I4,">0"),0) | P4: =IF(N4=1,SUMIF(I4,"<0")*-1,0) | Q4: =IF(M4=1,SUMIF(I4,"<0")*-1,0) | R4: =IF(M4=1,SUMIF(I4,">0"),0) | S4: =SUMIFS(I4,I4,"<0",M4,"",N4,"") | T4: =SUMIFS(I4,I4,">0",M4,"",N4,"") | U4: =IFERROR((S4*W4)*-1,0) | V4: =IFERROR(T4*W4,0) | W4: =VLOOKUP(B4,productos!A:K,5,FALSE) | X4: =VLOOKUP(B4,productos!A:K,4,FALSE)
A5: 45260 | B5: hy07235 | C5: soporte motor kia picanto morning 05 11 i10 09 15 tras | D5: effix | E5: soporte motor | F5: estante maquina inyectores - A | H5: =TEXT(A5,"MMMM") & TEXT(A5,"yy") | I5: 1 | O5: =IF(N5=1,SUMIF(I5,">0"),0) | P5: =IF(N5=1,SUMIF(I5,"<0")*-1,0) | Q5: =IF(M5=1,SUMIF(I5,"<0")*-1,0) | R5: =IF(M5=1,SUMIF(I5,">0"),0) | S5: =SUMIFS(I5,I5,"<0",M5,"",N5,"") | T5: =SUMIFS(I5,I5,">0",M5,"",N5,"") | U5: =IFERROR((S5*W5)*-1,0) | V5: =IFERROR(T5*W5,0) | W5: =VLOOKUP(B5,productos!A:K,5,FALSE) | X5: =VLOOKUP(B5,productos!A:K,4,FALSE)
A6: 45260 | B6: hy02002/25100-02400 | C6: bomba agua hyundai atos kia picanto 1,1 | D6: onnuri | E6: bomba de agua | F6: estante maquina inyectores - A | H6: =TEXT(A6,"MMMM") & TEXT(A6,"yy") | I6: 2 | O6: =IF(N6=1,SUMIF(I6,">0"),0) | P6: =IF(N6=1,SUMIF(I6,"<0")*-1,0) | Q6: =IF(M6=1,SUMIF(I6,"<0")*-1,0) | R6: =IF(M6=1,SUMIF(I6,">0"),0) | S6: =SUMIFS(I6,I6,"<0",M6,"",N6,"") | T6: =SUMIFS(I6,I6,">0",M6,"",N6,"") | U6: =IFERROR((S6*W6)*-1,0) | V6: =IFERROR(T6*W6,0) | W6: =VLOOKUP(B6,productos!A:K,5,FALSE) | X6: =VLOOKUP(B6,productos!A:K,4,FALSE)
A7: 45260 | B7: 7390-BKR5EY | C7: bujia copa 16 | D7: NGK | E7: bujias | F7: 12c | G7: 0 | H7: =TEXT(A7,"MMMM") & TEXT(A7,"yy") | I7: 6 | O7: =IF(N7=1,SUMIF(I7,">0"),0) | P7: =IF(N7=1,SUMIF(I7,"<0")*-1,0) | Q7: =IF(M7=1,SUMIF(I7,"<0")*-1,0) | R7: =IF(M7=1,SUMIF(I7,">0"),0) | S7: =SUMIFS(I7,I7,"<0",M7,"",N7,"") | T7: =SUMIFS(I7,I7,">0",M7,"",N7,"") | U7: =IFERROR((S7*W7)*-1,0) | V7: =IFERROR(T7*W7,0) | W7: =VLOOKUP(B7,productos!A:K,5,FALSE) | X7: =VLOOKUP(B7,productos!A:K,4,FALSE)
A8: 45260 | B8: cv01129/96325246 | C8: bomba aceite chevrolet spark 724 chronos daewoo matiz | D8: onnuri | E8: bomba de aceite | F8: estante maquina inyectores - A | H8: =TEXT(A8,"MMMM") & TEXT(A8,"yy") | I8: 1 | O8: =IF(N8=1,SUMIF(I8,">0"),0) | P8: =IF(N8=1,SUMIF(I8,"<0")*-1,0) | Q8: =IF(M8=1,SUMIF(I8,"<0")*-1,0) | R8: =IF(M8=1,SUMIF(I8,">0"),0) | S8: =SUMIFS(I8,I8,"<0",M8,"",N8,"") | T8: =SUMIFS(I8,I8,">0",M8,"",N8,"") | U8: =IFERROR((S8*W8)*-1,0) | V8: =IFERROR(T8*W8,0) | W8: =VLOOKUP(B8,productos!A:K,5,FALSE) | X8: =VLOOKUP(B8,productos!A:K,4,FALSE)
A9: 45260 | B9: rn07014 | C9: soporte motor renault megane 2 scenic 2 trasero | D9: effix | E9: soporte motor | F9: estante maquina inyectores - A | H9: =TEXT(A9,"MMMM") & TEXT(A9,"yy") | I9: 1 | O9: =IF(N9=1,SUMIF(I9,">0"),0) | P9: =IF(N9=1,SUMIF(I9,"<0")*-1,0) | Q9: =IF(M9=1,SUMIF(I9,"<0")*-1,0) | R9: =IF(M9=1,SUMIF(I9,">0"),0) | S9: =SUMIFS(I9,I9,"<0",M9,"",N9,"") | T9: =SUMIFS(I9,I9,">0",M9,"",N9,"") | U9: =IFERROR((S9*W9)*-1,0) | V9: =IFERROR(T9*W9,0) | W9: =VLOOKUP(B9,productos!A:K,5,FALSE) | X9: =VLOOKUP(B9,productos!A:K,4,FALSE)
A10: 45260 | B10: rn07131 | C10: tijera renault duster delantero derecha | D10: effix | E10: tijera | F10: 6a | H10: =TEXT(A10,"MMMM") & TEXT(A10,"yy") | I10: 2 | O10: =IF(N10=1,SUMIF(I10,">0"),0) | P10: =IF(N10=1,SUMIF(I10,"<0")*-1,0) | Q10: =IF(M10=1,SUMIF(I10,"<0")*-1,0) | R10: =IF(M10=1,SUMIF(I10,">0"),0) | S10: =SUMIFS(I10,I10,"<0",M10,"",N10,"") | T10: =SUMIFS(I10,I10,">0",M10,"",N10,"") | U10: =IFERROR((S10*W10)*-1,0) | V10: =IFERROR(T10*W10,0) | W10: =VLOOKUP(B10,productos!A:K,5,FALSE) | X10: =VLOOKUP(B10,productos!A:K,4,FALSE)
A11: 45260 | B11: hy01098 | C11: tensorcorrea reparticion atos santro kia picanto | D11: kbs | E11: tensor | F11: 2b-4c | H11: =TEXT(A11,"MMMM") & TEXT(A11,"yy") | I11: 7 | O11: =IF(N11=1,SUMIF(I11,">0"),0) | P11: =IF(N11=1,SUMIF(I11,"<0")*-1,0) | Q11: =IF(M11=1,SUMIF(I11,"<0")*-1,0) | R11: =IF(M11=1,SUMIF(I11,">0"),0) | S11: =SUMIFS(I11,I11,"<0",M11,"",N11,"") | T11: =SUMIFS(I11,I11,">0",M11,"",N11,"") | U11: =IFERROR((S11*W11)*-1,0) | V11: =IFERROR(T11*W11,0) | W11: =VLOOKUP(B11,productos!A:K,5,FALSE) | X11: =VLOOKUP(B11,productos!A:K,4,FALSE)
A12: 45260 | B12: cv01049/90499401 | C12: tensor correa distrivusion chevrolet corsa daewoo cielo racer aveo pequeño | D12: kbs | E12: rodamiento | H12: =TEXT(A12,"MMMM") & TEXT(A12,"yy") | I12: 10 | O12: =IF(N12=1,SUMIF(I12,">0"),0) | P12: =IF(N12=1,SUMIF(I12,"<0")*-1,0) | Q12: =IF(M12=1,SUMIF(I12,"<0")*-1,0) | R12: =IF(M12=1,SUMIF(I12,">0"),0) | S12: =SUMIFS(I12,I12,"<0",M12,"",N12,"") | T12: =SUMIFS(I12,I12,">0",M12,"",N12,"") | U12: =IFERROR((S12*W12)*-1,0) | V12: =IFERROR(T12*W12,0) | W12: =VLOOKUP(B12,productos!A:K,5,FALSE) | X12: =VLOOKUP(B12,productos!A:K,4,FALSE)
A13: 45260 | B13: cv08054 | C13: rodillo rueda del chev corsa | D13: kbs | E13: rodamiento | F13: 11d-a4 | H13: =TEXT(A13,"MMMM") & TEXT(A13,"yy") | I13: 4 | O13: =IF(N13=1,SUMIF(I13,">0"),0) | P13: =IF(N13=1,SUMIF(I13,"<0")*-1,0) | Q13: =IF(M13=1,SUMIF(I13,"<0")*-1,0) | R13: =IF(M13=1,SUMIF(I13,">0"),0) | S13: =SUMIFS(I13,I13,"<0",M13,"",N13,"") | T13: =SUMIFS(I13,I13,">0",M13,"",N13,"") | U13: =IFERROR((S13*W13)*-1,0) | V13: =IFERROR(T13*W13,0) | W13: =VLOOKUP(B13,productos!A:K,5,FALSE) | X13: =VLOOKUP(B13,productos!A:K,4,FALSE)
A14: 45260 | B14: rn8008 | C14: rodamiento tras renault logan sandero stepway bolas | D14: kbs | E14: rodamiento | F14: 2b-2b | H14: =TEXT(A14,"MMMM") & TEXT(A14,"yy") | I14: 1 | O14: =IF(N14=1,SUMIF(I14,">0"),0) | P14: =IF(N14=1,SUMIF(I14,"<0")*-1,0) | Q14: =IF(M14=1,SUMIF(I14,"<0")*-1,0) | R14: =IF(M14=1,SUMIF(I14,">0"),0) | S14: =SUMIFS(I14,I14,"<0",M14,"",N14,"") | T14: =SUMIFS(I14,I14,">0",M14,"",N14,"") | U14: =IFERROR((S14*W14)*-1,0) | V14: =IFERROR(T14*W14,0) | W14: =VLOOKUP(B14,productos!A:K,5,FALSE) | X14: =VLOOKUP(B14,productos!A:K,4,FALSE)
A15: 45260 | B15: rn08007 | C15: rodamiento rueda tras renault logan sandero agujas | D15: kbs | E15: rodamiento | F15: 2b-2a | H15: =TEXT(A15,"MMMM") & TEXT(A15,"yy") | I15: 1 | O15: =IF(N15=1,SUMIF(I15,">0"),0) | P15: =IF(N15=1,SUMIF(I15,"<0")*-1,0) | Q15: =IF(M15=1,SUMIF(I15,"<0")*-1,0) | R15: =IF(M15=1,SUMIF(I15,">0"),0) | S15: =SUMIFS(I15,I15,"<0",M15,"",N15,"") | T15: =SUMIFS(I15,I15,">0",M15,"",N15,"") | U15: =IFERROR((S15*W15)*-1,0) | V15: =IFERROR(T15*W15,0) | W15: =VLOOKUP(B15,productos!A:K,5,FALSE) | X15: =VLOOKUP(B15,productos!A:K,4,FALSE)
A16: 45260 | B16: hy08018/51720-2k00 | C16: rodamiento delantero hyundai i35 kia soul cerato forte koup veloster | D16: kbs | E16: rodamiento | F16: 11d-a7 | H16: =TEXT(A16,"MMMM") & TEXT(A16,"yy") | I16: 1 | O16: =IF(N16=1,SUMIF(I16,">0"),0) | P16: =IF(N16=1,SUMIF(I16,"<0")*-1,0) | Q16: =IF(M16=1,SUMIF(I16,"<0")*-1,0) | R16: =IF(M16=1,SUMIF(I16,">0"),0) | S16: =SUMIFS(I16,I16,"<0",M16,"",N16,"") | T16: =SUMIFS(I16,I16,">0",M16,"",N16,"") | U16: =IFERROR((S16*W16)*-1,0) | V16: =IFERROR(T16*W16,0) | W16: =VLOOKUP(B16,productos!A:K,5,FALSE) | X16: =VLOOKUP(B16,productos!A:K,4,FALSE)
A17: 45260 | B17: 24422061 | C17: balinera de clos corsa evolution onix soni | D17: supi | E17: balinera | F17: caja encintada | H17: =TEXT(A17,"MMMM") & TEXT(A17,"yy") | I17: 1 | O17: =IF(N17=1,SUMIF(I17,">0"),0) | P17: =IF(N17=1,SUMIF(I17,"<0")*-1,0) | Q17: =IF(M17=1,SUMIF(I17,"<0")*-1,0) | R17: =IF(M17=1,SUMIF(I17,">0"),0) | S17: =SUMIFS(I17,I17,"<0",M17,"",N17,"") | T17: =SUMIFS(I17,I17,">0",M17,"",N17,"") | U17: =IFERROR((S17*W17)*-1,0) | V17: =IFERROR(T17*W17,0) | W17: =VLOOKUP(B17,productos!A:K,5,FALSE) | X17: =VLOOKUP(B17,productos!A:K,4,FALSE)
A18: 45260 | B18: 30985x20 | C18: correa reparticion 125 dientes motor 200 daewoo espero aranos kadett ipanema monza | D18: gates | E18: correa reparticion | F18: 11e-a3 | H18: =TEXT(A18,"MMMM") & TEXT(A18,"yy") | I18: 1 | N18: 1 | O18: =IF(N18=1,SUMIF(I18,">0"),0) | P18: =IF(N18=1,SUMIF(I18,"<0")*-1,0) | Q18: =IF(M18=1,SUMIF(I18,"<0")*-1,0) | R18: =IF(M18=1,SUMIF(I18,">0"),0) | S18: =SUMIFS(I18,I18,"<0",M18,"",N18,"") | T18: =SUMIFS(I18,I18,">0",M18,"",N18,"") | U18: =IFERROR((S18*W18)*-1,0) | V18: =IFERROR(T18*W18,0) | W18: =VLOOKUP(B18,productos!A:K,5,FALSE) | X18: =VLOOKUP(B18,productos!A:K,4,FALSE)
A19: 45260 | B19: hy01096/24410-22020 | C19: tensor correa distribución hyundai accent next verna gyro vision rio xcite | D19: kbs | E19: rodamiento | F19: 11d-a5 | H19: =TEXT(A19,"MMMM") & TEXT(A19,"yy") | I19: 3 | O19: =IF(N19=1,SUMIF(I19,">0"),0) | P19: =IF(N19=1,SUMIF(I19,"<0")*-1,0) | Q19: =IF(M19=1,SUMIF(I19,"<0")*-1,0) | R19: =IF(M19=1,SUMIF(I19,">0"),0) | S19: =SUMIFS(I19,I19,"<0",M19,"",N19,"") | T19: =SUMIFS(I19,I19,">0",M19,"",N19,"") | U19: =IFERROR((S19*W19)*-1,0) | V19: =IFERROR(T19*W19,0) | W19: =VLOOKUP(B19,productos!A:K,5,FALSE) | X19: =VLOOKUP(B19,productos!A:K,4,FALSE)
A20: 45261 | B20: ABRABARR9 | C20: abrazadera barra estabilizadora r9 | D20: BOLSA SUELTO | E20: abrazadera barra estabilizadora | H20: =TEXT(A20,"MMMM") & TEXT(A20,"yy") | I20: 1 | O20: =IF(N20=1,SUMIF(I20,">0"),0) | P20: =IF(N20=1,SUMIF(I20,"<0")*-1,0) | Q20: =IF(M20=1,SUMIF(I20,"<0")*-1,0) | R20: =IF(M20=1,SUMIF(I20,">0"),0) | S20: =SUMIFS(I20,I20,"<0",M20,"",N20,"") | T20: =SUMIFS(I20,I20,">0",M20,"",N20,"") | U20: =IFERROR((S20*W20)*-1,0) | V20: =IFERROR(T20*W20,0) | W20: =VLOOKUP(B20,productos!A:K,5,FALSE) | X20: =VLOOKUP(B20,productos!A:K,4,FALSE)
A21: 45261 | B21: 3/4abraza | C21: abrazadera metalica 3/4 pulgadas pequeña | D21: BOLSA TRANSPARENTE | E21: abrazadera metalica | H21: =TEXT(A21,"MMMM") & TEXT(A21,"yy") | I21: 23 | O21: =IF(N21=1,SUMIF(I21,">0"),0) | P21: =IF(N21=1,SUMIF(I21,"<0")*-1,0) | Q21: =IF(M21=1,SUMIF(I21,"<0")*-1,0) | R21: =IF(M21=1,SUMIF(I21,">0"),0) | S21: =SUMIFS(I21,I21,"<0",M21,"",N21,"") | T21: =SUMIFS(I21,I21,">0",M21,"",N21,"") | U21: =IFERROR((S21*W21)*-1,0) | V21: =IFERROR(T21*W21,0) | W21: =VLOOKUP(B21,productos!A:K,5,FALSE) | X21: =VLOOKUP(B21,productos!A:K,4,FALSE)
A22: 45261 | B22: abrametcom | C22: abrazadera metalica comun que mas hay | D22: suelta | E22: abrazadera metalica | H22: =TEXT(A22,"MMMM") & TEXT(A22,"yy") | I22: 2 | O22: =IF(N22=1,SUMIF(I22,">0"),0) | P22: =IF(N22=1,SUMIF(I22,"<0")*-1,0) | Q22: =IF(M22=1,SUMIF(I22,"<0")*-1,0) | R22: =IF(M22=1,SUMIF(I22,">0"),0) | S22: =SUMIFS(I22,I22,"<0",M22,"",N22,"") | T22: =SUMIFS(I22,I22,">0",M22,"",N22,"") | U22: =IFERROR((S22*W22)*-1,0) | V22: =IFERROR(T22*W22,0) | W22: =VLOOKUP(B22,productos!A:K,5,FALSE) | X22: =VLOOKUP(B22,productos!A:K,4,FALSE)
A23: 45261 | B23: abra1004 | C23: abrazaderametalica titan para manguera 3/8 pulgadas. min 5/16'' max 5/8'' | D23: titan bolsa | E23: abrazadera metalica | H23: =TEXT(A23,"MMMM") & TEXT(A23,"yy") | I23: 3 | O23: =IF(N23=1,SUMIF(I23,">0"),0) | P23: =IF(N23=1,SUMIF(I23,"<0")*-1,0) | Q23: =IF(M23=1,SUMIF(I23,"<0")*-1,0) | R23: =IF(M23=1,SUMIF(I23,">0"),0) | S23: =SUMIFS(I23,I23,"<0",M23,"",N23,"") | T23: =SUMIFS(I23,I23,">0",M23,"",N23,"") | U23: =IFERROR((S23*W23)*-1,0) | V23: =IFERROR(T23*W23,0) | W23: =VLOOKUP(B23,productos!A:K,5,FALSE) | X23: =VLOOKUP(B23,productos!A:K,4,FALSE)
A24: 45261 | B24: abra1006 | C24: abrazdadera metalica titan para manguera 1/2 pulgada min 7/16'' max 25/32'' | D24: titan bolsa | E24: abrazadera metalica | H24: =TEXT(A24,"MMMM") & TEXT(A24,"yy") | I24: 1 | O24: =IF(N24=1,SUMIF(I24,">0"),0) | P24: =IF(N24=1,SUMIF(I24,"<0")*-1,0) | Q24: =IF(M24=1,SUMIF(I24,"<0")*-1,0) | R24: =IF(M24=1,SUMIF(I24,">0"),0) | S24: =SUMIFS(I24,I24,"<0",M24,"",N24,"") | T24: =SUMIFS(I24,I24,">0",M24,"",N24,"") | U24: =IFERROR((S24*W24)*-1,0) | V24: =IFERROR(T24*W24,0) | W24: =VLOOKUP(B24,productos!A:K,5,FALSE) | X24: =VLOOKUP(B24,productos!A:K,4,FALSE)
A25: 45261 | B25: abra4028 | C25: abrazadera metalica titan min 1*1/4'' max 2'' | D25: titan bolsa | E25: abrazadera metalica | H25: =TEXT(A25,"MMMM") & TEXT(A25,"yy") | I25: 2 | O25: =IF(N25=1,SUMIF(I25,">0"),0) | P25: =IF(N25=1,SUMIF(I25,"<0")*-1,0) | Q25: =IF(M25=1,SUMIF(I25,"<0")*-1,0) | R25: =IF(M25=1,SUMIF(I25,">0"),0) | S25: =SUMIFS(I25,I25,"<0",M25,"",N25,"") | T25: =SUMIFS(I25,I25,">0",M25,"",N25,"") | U25: =IFERROR((S25*W25)*-1,0) | V25: =IFERROR(T25*W25,0) | W25: =VLOOKUP(B25,productos!A:K,5,FALSE) | X25: =VLOOKUP(B25,productos!A:K,4,FALSE)
A26: 45261 | B26: abra4016 | C26: abrazadera metalica titan min 23 max 35 mm | D26: titan bolsa | E26: abrazadera metalica | H26: =TEXT(A26,"MMMM") & TEXT(A26,"yy") | I26: 34 | O26: =IF(N26=1,SUMIF(I26,">0"),0) | P26: =IF(N26=1,SUMIF(I26,"<0")*-1,0) | Q26: =IF(M26=1,SUMIF(I26,"<0")*-1,0) | R26: =IF(M26=1,SUMIF(I26,">0"),0) | S26: =SUMIFS(I26,I26,"<0",M26,"",N26,"") | T26: =SUMIFS(I26,I26,">0",M26,"",N26,"") | U26: =IFERROR((S26*W26)*-1,0) | V26: =IFERROR(T26*W26,0) | W26: =VLOOKUP(B26,productos!A:K,5,FALSE) | X26: =VLOOKUP(B26,productos!A:K,4,FALSE)
A27: 45261 | B27: MK-131-N | C27: abrazadera larga y ancha plástica 7,2*500 mm | D27: MAK | E27: abrazaderas | H27: =TEXT(A27,"MMMM") & TEXT(A27,"yy") | I27: 4 | O27: =IF(N27=1,SUMIF(I27,">0"),0) | P27: =IF(N27=1,SUMIF(I27,"<0")*-1,0) | Q27: =IF(M27=1,SUMIF(I27,"<0")*-1,0) | R27: =IF(M27=1,SUMIF(I27,">0"),0) | S27: =SUMIFS(I27,I27,"<0",M27,"",N27,"") | T27: =SUMIFS(I27,I27,">0",M27,"",N27,"") | U27: =IFERROR((S27*W27)*-1,0) | V27: =IFERROR(T27*W27,0) | W27: =VLOOKUP(B27,productos!A:K,5,FALSE) | X27: =VLOOKUP(B27,productos!A:K,4,FALSE)
A28: 45261 | B28: mk-125-n | C28: abrazadera plastica mediana de 4,8* 300mm | D28: mak | E28: abrazaderas | H28: =TEXT(A28,"MMMM") & TEXT(A28,"yy") | I28: 3 | O28: =IF(N28=1,SUMIF(I28,">0"),0) | P28: =IF(N28=1,SUMIF(I28,"<0")*-1,0) | Q28: =IF(M28=1,SUMIF(I28,"<0")*-1,0) | R28: =IF(M28=1,SUMIF(I28,">0"),0) | S28: =SUMIFS(I28,I28,"<0",M28,"",N28,"") | T28: =SUMIFS(I28,I28,">0",M28,"",N28,"") | U28: =IFERROR((S28*W28)*-1,0) | V28: =IFERROR(T28*W28,0) | W28: =VLOOKUP(B28,productos!A:K,5,FALSE) | X28: =VLOOKUP(B28,productos!A:K,4,FALSE)
A29: 45261 | B29: mk-127-n | C29: abrazadea plastico 4,8*400mm | D29: mak | E29: abrazaderas | H29: =TEXT(A29,"MMMM") & TEXT(A29,"yy") | I29: 2 | O29: =IF(N29=1,SUMIF(I29,">0"),0) | P29: =IF(N29=1,SUMIF(I29,"<0")*-1,0) | Q29: =IF(M29=1,SUMIF(I29,"<0")*-1,0) | R29: =IF(M29=1,SUMIF(I29,">0"),0) | S29: =SUMIFS(I29,I29,"<0",M29,"",N29,"") | T29: =SUMIFS(I29,I29,">0",M29,"",N29,"") | U29: =IFERROR((S29*W29)*-1,0) | V29: =IFERROR(T29*W29,0) | W29: =VLOOKUP(B29,productos!A:K,5,FALSE) | X29: =VLOOKUP(B29,productos!A:K,4,FALSE)
A30: 45261 | B30: mk-129-n | C30: abrazadera plastica 4,8*200 pequeña | D30: MAK | E30: abrazaderas | H30: =TEXT(A30,"MMMM") & TEXT(A30,"yy") | I30: 2 | O30: =IF(N30=1,SUMIF(I30,">0"),0) | P30: =IF(N30=1,SUMIF(I30,"<0")*-1,0) | Q30: =IF(M30=1,SUMIF(I30,"<0")*-1,0) | R30: =IF(M30=1,SUMIF(I30,">0"),0) | S30: =SUMIFS(I30,I30,"<0",M30,"",N30,"") | T30: =SUMIFS(I30,I30,">0",M30,"",N30,"") | U30: =IFERROR((S30*W30)*-1,0) | V30: =IFERROR(T30*W30,0) | W30: =VLOOKUP(B30,productos!A:K,5,FALSE) | X30: =VLOOKUP(B30,productos!A:K,4,FALSE)
A31: 45261 | B31: 5W-30 | C31: aceite 1/4 mobil super 5w-30 3000 | D31: MOBIL | E31: aceite | H31: =TEXT(A31,"MMMM") & TEXT(A31,"yy") | I31: 3 | O31: =IF(N31=1,SUMIF(I31,">0"),0) | P31: =IF(N31=1,SUMIF(I31,"<0")*-1,0) | Q31: =IF(M31=1,SUMIF(I31,"<0")*-1,0) | R31: =IF(M31=1,SUMIF(I31,">0"),0) | S31: =SUMIFS(I31,I31,"<0",M31,"",N31,"") | T31: =SUMIFS(I31,I31,">0",M31,"",N31,"") | U31: =IFERROR((S31*W31)*-1,0) | V31: =IFERROR(T31*W31,0) | W31: =VLOOKUP(B31,productos!A:K,5,FALSE) | X31: =VLOOKUP(B31,productos!A:K,4,FALSE)
... A45: 45262 | B45: SAE50M | C45: aceite 1/4 sae 50 mobil special hd | D45: MOBIL | E45: aceite | H45: =TEXT(A45,"MMMM") & TEXT(A45,"yy") | I45: -1 | O45: =IF(N45=1,SUMIF(I45,">0"),0) | P45: =IF(N45=1,SUMIF(I45,"<0")*-1,0) | Q45: =IF(M45=1,SUMIF(I45,"<0")*-1,0) | R45: =IF(M45=1,SUMIF(I45,">0"),0) | S45: =SUMIFS(I45,I45,"<0",M45,"",N45,"") | T45: =SUMIFS(I45,I45,">0",M45,"",N45,"") | U45: =IFERROR((S45*W45)*-1,0) | V45: =IFERROR(T45*W45,0) | W45: =VLOOKUP(B45,productos!A:K,5,FALSE) | X45: =VLOOKUP(B45,productos!A:K,4,FALSE)
